{
  "type": "parcool_set_stamina_recovery_attribute",
  "message0": "Set ParCool stamina recovery of %1 to %2",
  "args0": [
    { "type": "input_value", "name": "ENTITY", "check": "Entity" },
    { "type": "input_value", "name": "VALUE", "check": "Number" }
  ],
  "inputsInline": true,
  "previousStatement": null,
  "nextStatement": null,
  "colour": 220,
  "tooltip": "Set current STAMINA_RECOVERY attribute value.",
  "helpUrl": "",
  "mcreator": {
    "toolbox_id": "parcool_api",
    "inputs": ["ENTITY", "VALUE"]
  }
}